altair_saver/__init__.py
altair_saver/_core.py
altair_saver/_utils.py
altair_saver/types.py
altair_saver/savers/__init__.py
altair_saver/savers/_basic.py
altair_saver/savers/_html.py
altair_saver/savers/_node.py
altair_saver/savers/_saver.py
altair_saver/savers/_selenium.py
altair_saver/savers/tests/__init__.py
altair_saver/savers/tests/test_basic.py
altair_saver/savers/tests/test_html.py
altair_saver/savers/tests/test_node.py
altair_saver/savers/tests/test_selenium.py
altair_saver/savers/tests/testcases/bar.pdf
altair_saver/savers/tests/testcases/bar.png
altair_saver/savers/tests/testcases/bar.svg
altair_saver/savers/tests/testcases/bar.vg.json
altair_saver/savers/tests/testcases/bar.vl.json
altair_saver/savers/tests/testcases/scatter.pdf
altair_saver/savers/tests/testcases/scatter.png
altair_saver/savers/tests/testcases/scatter.svg
altair_saver/savers/tests/testcases/scatter.vg.json
altair_saver/savers/tests/testcases/scatter.vl.json
altair_saver/tests/__init__.py
altair_saver/tests/test_core.py
altair_saver/tests/test_entrypoint.py
altair_saver/tests/test_utils.py
altair_saver-0.4.0.dist-info/LICENSE
altair_saver-0.4.0.dist-info/METADATA
altair_saver-0.4.0.dist-info/WHEEL
altair_saver-0.4.0.dist-info/entry_points.txt
altair_saver-0.4.0.dist-info/top_level.txt
altair_saver-0.4.0.dist-info/RECORD
