Metadata-Version: 2.1
Name: altair-saver
Version: 0.4.0
Summary: Altair extension for saving charts to various formats.
Home-page: http://github.com/altair-viz/altair_saver/
Author: Jake VanderPlas
Author-email: jakevdp@gmail.com
License: MIT
Download-URL: http://github.com/altair-viz/altair_saver/
Platform: UNKNOWN
Classifier: Environment :: Console
Classifier: Intended Audience :: Science/Research
Classifier: License :: OSI Approved :: BSD License
Classifier: Natural Language :: English
Classifier: Programming Language :: Python :: 3.6
Classifier: Programming Language :: Python :: 3.7
Classifier: Programming Language :: Python :: 3.8
Requires-Python: >=3.6
Requires-Dist: altair
Requires-Dist: altair-data-server (>=0.4.0)
Requires-Dist: altair-viewer
Requires-Dist: selenium
